{"jsonrpc":"2.0","result":{"context":{"apiVersion":"2.2.19","slot":30329721},"value":[{"address":"3bQvcXYPiD7AUFHsidJzmKJo2U4RX81mrTveuXBunhQ9","amount":"211448272168910","decimals":9,"uiAmount":211448.27216891,"uiAmountString":"211448.27216891"},{"address":"2SP5VzXU86JMr3oZXxwakzBHP5ZDf9T3LNaAZbctjiG9","amount":"209155274090719","decimals":9,"uiAmount":209155.274090719,"uiAmountString":"209155.274090719"},{"address":"FBJyBQBiafxk2UnVKxWtfvCPGHdyuQY14y9LTB5weSzF","amount":"188490000112830","decimals":9,"uiAmount":188490.00011283,"uiAmountString":"188490.00011283"},{"address":"GLL5KQfLBQknLyyh6FxSVaeudM5HgiZKcVKE8AZG2ty3","amount":"57650727693390","decimals":9,"uiAmount":57650.72769339,"uiAmountString":"57650.72769339"},{"address":"2xGxAw3gH6nJmDxEWmUbT3cu2fWdwReTW77rUs8aarqA","amount":"54984496561263","decimals":9,"uiAmount":54984.496561263,"uiAmountString":"54984.496561263"},{"address":"8nDwf9PFgnotsfveC3iZXg3ZRkPkXhD4jKSCpfVmAMaR","amount":"50221715038893","decimals":9,"uiAmount":50221.715038893,"uiAmountString":"50221.715038893"},{"address":"DHWgzQNdYzCF2MUv16fc1oPxNMFNWM48TRNHkS2BZ1x6","amount":"50003802026121","decimals":9,"uiAmount":50003.802026121,"uiAmountString":"50003.802026121"},{"address":"CvHUwL85tewrTjJCBRT2jmVNUo2zKJefk1sWs4oUAyxr","amount":"31849788086952","decimals":9,"uiAmount":31849.788086952,"uiAmountString":"31849.788086952"},{"address":"38DbzD85mvT1oG6W9trn6dKcv5arMJKgQXauBCVZmYKX","amount":"30088342357774","decimals":9,"uiAmount":30088.342357774,"uiAmountString":"30088.342357774"},{"address":"9WfNTQUfxFa7HWt2sMdC4EtWnKtsMxiZAt7yZQNtwspe","amount":"20261454538242","decimals":9,"uiAmount":20261.454538242,"uiAmountString":"20261.454538242"},{"address":"AvbFf7gDEEK67rh5fyRjCkWK9kDR3YvbzdZxjfbAEP7a","amount":"17704140796383","decimals":9,"uiAmount":17704.140796383,"uiAmountString":"17704.140796383"},{"address":"AK224Fowx1Qp58dvZ8RQvQFfnbW31DSweyydvoRC7uH2","amount":"17361998851911","decimals":9,"uiAmount":17361.998851911,"uiAmountString":"17361.998851911"},{"address":"54r2EwNZhSMxeEsGdhZZVZeUnhoo5vQXwQkd9n2uMSDL","amount":"15596542321170","decimals":9,"uiAmount":15596.54232117,"uiAmountString":"15596.54232117"},{"address":"Bdy1s4uAmpbSM4hDvgSxAbLVqrNEFDXUtNMRUPLffqwb","amount":"9638303387914","decimals":9,"uiAmount":9638.303387914,"uiAmountString":"9638.303387914"},{"address":"6ZVuhhcs3VmMZyVgtiRGZNhqTG17GfzrKa5RX21iyRwU","amount":"7138803960243","decimals":9,"uiAmount":7138.803960243,"uiAmountString":"7138.803960243"},{"address":"4YMhuCqpAZUY9XugSQF6BvHCcpJpQxcEwS8tn6ewiq7b","amount":"6938112180850","decimals":9,"uiAmount":6938.11218085,"uiAmountString":"6938.11218085"},{"address":"81daMQQ4HNB1tZNQEmCzM7VJkKJDRwznm9CJKmbLkvDb","amount":"5380017505792","decimals":9,"uiAmount":5380.017505792,"uiAmountString":"5380.017505792"},{"address":"HSJzNRCrtDdiHP7GbHFgnKCUs1AecaoF1JmoRUQ63Pp","amount":"5101543268619","decimals":9,"uiAmount":5101.543268619,"uiAmountString":"5101.543268619"},{"address":"HJjzT1Y11AS5JC24dDprX4qMWjR2y1VqUYBUyiGUC3s6","amount":"1555980398657","decimals":9,"uiAmount":1555.980398657,"uiAmountString":"1555.980398657"},{"address":"HW3fEvVbD2fL9eVYhQFbG7Nj4fohwZpA3Adfkt5K6yiG","amount":"1111067913160","decimals":9,"uiAmount":1111.06791316,"uiAmountString":"1111.06791316"}]},"id":1}
